provit/__init__.py
provit/agent.py
provit/cli.py
provit/config.py
provit/home.py
provit/namespaces.py
provit/prov.py
provit/utils.py
provit/browser/__init__.py
provit/browser/backend.py
provit/browser/static/css/2.e59c9b8d.chunk.css
provit/browser/static/css/main.2cb06cb3.chunk.css
provit/browser/static/js/2.5ed59993.chunk.js
provit/browser/static/js/main.27ef1ec9.chunk.js
provit/browser/static/js/main.437a8b1d.chunk.js
provit/browser/static/js/main.46bff27a.chunk.js
provit/browser/static/js/main.834f7bf7.chunk.js
provit/browser/static/js/main.aa60d8d4.chunk.js
provit/browser/static/js/runtime~main.a8a9905a.js
provit/browser/templates/index.html
provit/tests/__init__.py
provit/tests/conftest.py
provit/tests/test_agent.py
provit/tests/test_backend.py
provit/tests/test_cli.py
provit/tests/test_config.py
provit/tests/test_home.py
provit/tests/test_prov.py
provit/tests/test_utils.py
provit-1.1.1.dist-info/LICENSE
provit-1.1.1.dist-info/METADATA
provit-1.1.1.dist-info/WHEEL
provit-1.1.1.dist-info/entry_points.txt
provit-1.1.1.dist-info/top_level.txt
provit-1.1.1.dist-info/RECORD
