Metadata-Version: 2.1
Name: provit
Version: 1.1.1
Summary: A light, dezentralized provenance tracking framework using the W3C PROV-O vocabulary
Home-page: https://github.com/diggr/provit
Author: Diggr Team
Author-email: team@diggr.link
License: MIT
Keywords: provenance,cli,model,PROV,PROV-DM,PROV-JSON,JSON,PROV-XML,PROV-N,PROV-O,RDF,JSON-LD
Platform: UNKNOWN
Classifier: Development Status :: 3 - Alpha
Classifier: Environment :: Console
Classifier: Environment :: Web Environment
Classifier: Intended Audience :: Developers
Classifier: Intended Audience :: Information Technology
Classifier: Intended Audience :: Science/Research
Classifier: License :: OSI Approved :: MIT License
Classifier: Natural Language :: English
Classifier: Operating System :: OS Independent
Classifier: Programming Language :: Python :: 3
Classifier: Programming Language :: Python :: 3.5
Classifier: Programming Language :: Python :: 3.6
Classifier: Programming Language :: Python :: Implementation :: CPython
Classifier: Programming Language :: Python :: Implementation :: PyPy
Classifier: Topic :: Scientific/Engineering
Classifier: Topic :: Scientific/Engineering :: Information Analysis
Classifier: Topic :: System :: Logging
Requires-Dist: click (==7.0)
Requires-Dist: flask (==1.0.3)
Requires-Dist: flask-cors (==3.0.8)
Requires-Dist: isodate (==0.6.0)
Requires-Dist: itsdangerous (==1.1.0)
Requires-Dist: jinja2 (==2.10.3)
Requires-Dist: markupsafe (==1.1.1)
Requires-Dist: prompt-toolkit (==3.0.2)
Requires-Dist: pyparsing (==2.4.5)
Requires-Dist: pyyaml (==5.1.1)
Requires-Dist: rdflib-jsonld (==0.4.0)
Requires-Dist: rdflib (==4.2.2)
Requires-Dist: six (==1.13.0)
Requires-Dist: wcwidth (==0.1.7)
Requires-Dist: werkzeug (==0.16.0)
